{
  "fixed_scale_k": 16,
  "x": [
    82658,
    10834,
    -16147,
    114292
  ],
  "y_target": [
    86646,
    43210,
    -147066,
    -82965
  ],
  "lr_scaled": 655,
  "w1_before": [
    [
      -25360,
      17005,
      30310,
      -28839
    ],
    [
      8382,
      -17164,
      19931,
      21424
    ],
    [
      -24862,
      -15362,
      23096,
      -926
    ],
    [
      9146,
      28471,
      17127,
      -17835
    ]
  ],
  "b1_before": [
    -10074,
    -1335,
    20825,
    1004
  ],
  "w2_before": [
    [
      -8935,
      20965,
      31962,
      15659
    ],
    [
      3058,
      13834,
      -27120,
      4297
    ],
    [
      -27333,
      17034,
      25228,
      -451
    ],
    [
      -18767,
      22192,
      24529,
      24686
    ]
  ],
  "b2_before": [
    -17776,
    -30255,
    -18335,
    -8240
  ],
  "w1_after": [
    [
      -25360,
      17005,
      30310,
      -28839
    ],
    [
      8194,
      -17189,
      19968,
      21165
    ],
    [
      -24862,
      -15362,
      23096,
      -926
    ],
    [
      9146,
      28471,
      17127,
      -17835
    ]
  ],
  "b1_after": [
    -10074,
    -1483,
    20825,
    1004
  ],
  "w2_after": [
    [
      -8935,
      20965,
      31962,
      15659
    ],
    [
      3058,
      13834,
      -27120,
      4297
    ],
    [
      -27333,
      17034,
      25228,
      -451
    ],
    [
      -18767,
      21932,
      24529,
      24686
    ]
  ],
  "b2_after": [
    -17776,
    -30255,
    -18335,
    -8680
  ],
  "z1": [
    -97011,
    38852,
    -20377,
    -18078
  ],
  "a1": [
    0,
    38852,
    0,
    0
  ],
  "z2": [
    -5347,
    -22054,
    -8237,
    4916
  ],
  "y_pred": [
    0,
    0,
    0,
    4916
  ],
  "grad_y": [
    -43323,
    -21605,
    73533,
    43940
  ],
  "grad_z2": [
    0,
    0,
    0,
    43940
  ],
  "grad_a1": [
    -12583,
    14879,
    16446,
    16552
  ],
  "grad_z1": [
    0,
    14879,
    0,
    0
  ],
  "grad_x": [
    1903,
    -3897,
    4525,
    4864
  ],
  "grad_w1": [
    [
      0,
      0,
      0,
      0
    ],
    [
      18767,
      2460,
      -3666,
      25949
    ],
    [
      0,
      0,
      0,
      0
    ],
    [
      0,
      0,
      0,
      0
    ]
  ],
  "grad_b1": [
    0,
    14879,
    0,
    0
  ],
  "grad_w2": [
    [
      0,
      0,
      0,
      0
    ],
    [
      0,
      0,
      0,
      0
    ],
    [
      0,
      0,
      0,
      0
    ],
    [
      0,
      26049,
      0,
      0
    ]
  ],
  "grad_b2": [
    0,
    0,
    0,
    43940
  ]
}